MANIFEST.in
README.rst
__version__.py
setup.py
smartcp.py
smartcp.egg-info/PKG-INFO
smartcp.egg-info/SOURCES.txt
smartcp.egg-info/dependency_links.txt
smartcp.egg-info/entry_points.txt
smartcp.egg-info/requires.txt
smartcp.egg-info/top_level.txt