Metadata-Version: 1.1
Name: smartcp
Version: 0.2
Summary: Smart Copy Utility
Home-page: http://www.github.com/blegat/smartcp
Author: Benoît Legat
Author-email: benoit.legat@gmail.com
License: GPLv3+
Platform: UNKNOWN
Classifier: Development Status :: 4 - Beta
Classifier: Environment :: Console
Classifier: License :: OSI Approved :: GNU General Public License v3 or later (GPLv3+)
Classifier: Programming Language :: Python :: 3
Classifier: Programming Language :: Python :: 3.3
Classifier: Topic :: Utilities
